{"id":"smart_valve_blogs_advanced","type":"SharedSlice","name":"SmartValveBlogsAdvanced","description":"Carousel of blog cards with curve/depth effect (type: smartvalve)","variations":[{"id":"default","name":"Default","docURL":"","version":"initial","description":"Advanced carousel with 3D effect","imageUrl":"","primary":{"section_title":{"type":"Text","config":{"label":"Section Title","placeholder":"Latest from SmartValve"}},"background_color":{"type":"Color","config":{"label":"Background Color","placeholder":"#0a0a0a"}}},"items":{}}]}
