[{"__TYPE__":"SharedSliceContent","variation":"default","primary":{"title":{"__TYPE__":"FieldContent","value":"Innovation Meets Precision","type":"Text"},"subtitle":{"__TYPE__":"StructuredTextContent","value":[{"type":"paragraph","content":{"text":"Discover our cutting-edge valve technology that combines advanced engineering with intelligent control systems for optimal performance in any environment."}}]},"button_text":{"__TYPE__":"FieldContent","value":"Explore Our Technology","type":"Text"},"button_link":{"__TYPE__":"LinkContent","type":"Link.web","value":{"url":"https://example.com/technology","target":"_blank"}},"background_image":{"__TYPE__":"ImageContent","url":"https://images.unsplash.com/photo-1581091226825-a6a2a5aee158?w=1920","alt":null,"copyright":null,"dimensions":{"width":1920,"height":1080},"placeholder":null},"background_image_mode":{"__TYPE__":"FieldContent","value":"cover","type":"Select"},"overlay_opacity":{"__TYPE__":"FieldContent","value":"medium","type":"Select"},"background_color":{"__TYPE__":"FieldContent","value":"#0a0a0a","type":"Color"}},"items":[]}]
